MANIFEST.in
setup.py
dashboard/Link.py
dashboard/__init__.py
dashboard/links.py
dashboard/providers.py
dashboard/routes.py
dashboard/controllers/AuthenticationController.py
dashboard/controllers/DashboardController.py
dashboard/controllers/UserManagementController.py
dashboard/static/.DS_Store
dashboard/static/style.css
dashboard/templates/dashboard/.DS_Store
dashboard/templates/dashboard/base.html
dashboard/templates/dashboard/index.html
dashboard/templates/dashboard/login.html
dashboard/templates/dashboard/show.html
dashboard/templates/dashboard/sidebar.html
dashboard/templates/dashboard/single.html
masonite_dashboard.egg-info/PKG-INFO
masonite_dashboard.egg-info/SOURCES.txt
masonite_dashboard.egg-info/dependency_links.txt
masonite_dashboard.egg-info/top_level.txt