Metadata-Version: 1.0
Name: masonite-dashboard
Version: 0.1.3
Summary: Masonite Dashboard
Home-page: https://github.com/MasoniteFramework/masonite
Author: Joseph Mancuso
Author-email: idmann509@gmail.com
License: UNKNOWN
Keywords: python web framework,python3
Platform: UNKNOWN
